mseep_prometheus_mcp_server-1.2.9.dist-info/licenses/LICENSE
prometheus_mcp_server/__init__.py
prometheus_mcp_server/logging_config.py
prometheus_mcp_server/main.py
prometheus_mcp_server/server.py
mseep_prometheus_mcp_server-1.2.9.dist-info/METADATA
mseep_prometheus_mcp_server-1.2.9.dist-info/WHEEL
mseep_prometheus_mcp_server-1.2.9.dist-info/entry_points.txt
mseep_prometheus_mcp_server-1.2.9.dist-info/top_level.txt
mseep_prometheus_mcp_server-1.2.9.dist-info/RECORD
