Metadata-Version: 2.4
Name: mseep-prometheus_mcp_server
Version: 1.2.9
Summary: MCP server for Prometheus integration
Author-email: mseep <support@skydeck.ai>
Requires-Python: >=3.10
License-File: LICENSE
Requires-Dist: mcp[cli]
Requires-Dist: prometheus-api-client
Requires-Dist: python-dotenv
Requires-Dist: pyproject-toml>=0.1.0
Requires-Dist: requests
Requires-Dist: structlog>=23.0.0
Requires-Dist: fastmcp>=2.11.3
Provides-Extra: dev
Requires-Dist: pytest>=7.0.0; extra == "dev"
Requires-Dist: pytest-cov>=4.0.0; extra == "dev"
Requires-Dist: pytest-asyncio>=0.21.0; extra == "dev"
Requires-Dist: pytest-mock>=3.10.0; extra == "dev"
Requires-Dist: docker>=7.0.0; extra == "dev"
Requires-Dist: requests>=2.31.0; extra == "dev"
Dynamic: license-file
